pyscan/__init__.py
pyscan/libann.so
pyscan/libappext.so
pyscan/libdiscrepancy.so
pyscan/libpyscan.cpython-38-x86_64-linux-gnu.so
pyscan/pyscan.py
pyscan_stats.libs/libgmp-d944b113.so.10.3.2
pyscan_stats.libs/libgmpxx-8b3a383a.so.4.5.2
pyscan_stats.libs/libgsl-b64c76bc.so.23.1.0
pyscan_stats.libs/libgslcblas-cd2c2030.so.0.0.0
pyscan_stats.libs/libmpfr-b7fafdf8.so.4.1.6
pyscan_stats-1.0.2.dist-info/METADATA
pyscan_stats-1.0.2.dist-info/WHEEL
pyscan_stats-1.0.2.dist-info/RECORD
pyscan_stats-1.0.2.dist-info/licenses/LICENSE
