Metadata-Version: 2.2
Name: pyscan-stats
Version: 1.0.2
Summary: C++ spatial scan wrapper for Python
Author: Michael Matheny
License: MIT License
Requires-Python: >=3.8
Provides-Extra: dev
Requires-Dist: scikit-build-core; extra == "dev"
Requires-Dist: cmake; extra == "dev"
Requires-Dist: ninja; extra == "dev"
Requires-Dist: pybind11; extra == "dev"
Requires-Dist: pybind11-global; extra == "dev"
Requires-Dist: twine; extra == "dev"
Requires-Dist: build; extra == "dev"
Requires-Dist: cibuildwheel; extra == "dev"
Provides-Extra: utils
Requires-Dist: geopandas>=0.13.2; extra == "utils"
Requires-Dist: matplotlib>=3.7.5; extra == "utils"
Requires-Dist: pandas>=2.0.3; extra == "utils"
Requires-Dist: pyqt6>=6.7.1; extra == "utils"
Requires-Dist: shapely>=2.0.7; extra == "utils"
Requires-Dist: seaborn>=0.13.2; extra == "utils"
Requires-Dist: tqdm>=4.67.1; extra == "utils"
Requires-Dist: xarray>=2025.1.1; extra == "utils"
Requires-Dist: h5netcdf>=1.6.3; extra == "utils"
